dasima/__init__.py
dasima/consumer.py
dasima/exchange.py
dasima/producer.py
example/__init__.py
example/test_flask_client.py
example/test_flask_server.py
dasima-1.0.3.dist-info/LICENSE
dasima-1.0.3.dist-info/METADATA
dasima-1.0.3.dist-info/WHEEL
dasima-1.0.3.dist-info/top_level.txt
dasima-1.0.3.dist-info/RECORD
