Metadata-Version: 2.1
Name: dasima
Version: 1.0.3
Summary: Message Queue Tools for flask project
Home-page: https://github.com/linewalks/dasima
Author: Linewalks
Author-email: jindex2411@linewalks.com
License: Linewalks
Requires-Python: >=3.6
License-File: LICENSE
Requires-Dist: Flask
Requires-Dist: kombu
